laundrify_aio/__init__.py
laundrify_aio/errors.py
laundrify_aio/exceptions.py
laundrify_aio/laundrify_device.py
laundrify_aio/utils.py
laundrify_aio-1.2.2.dist-info/LICENSE
laundrify_aio-1.2.2.dist-info/METADATA
laundrify_aio-1.2.2.dist-info/WHEEL
laundrify_aio-1.2.2.dist-info/top_level.txt
laundrify_aio-1.2.2.dist-info/RECORD
