Metadata-Version: 2.1
Name: laundrify_aio
Version: 1.2.2
Summary: A Python package to communicate with the laundrify API
Home-page: https://github.com/laundrify/laundrify-pypi
Author: Mike Mülhaupt
Author-email: mike@laundrify.de
License: MIT
Keywords: home-assistant,laundrify
Platform: UNKNOWN
Classifier: License :: OSI Approved :: MIT License
Classifier: Programming Language :: Python :: 3
Classifier: Programming Language :: Python :: 3.7
Classifier: Intended Audience :: Developers
